README.md
setup.py
brazil_national_days/__init__.py
brazil_national_days/client.py
brazil_national_days/controller.py
brazil_national_days.egg-info/PKG-INFO
brazil_national_days.egg-info/SOURCES.txt
brazil_national_days.egg-info/dependency_links.txt
brazil_national_days.egg-info/requires.txt
brazil_national_days.egg-info/top_level.txt