Metadata-Version: 2.1
Name: brazil-national-days
Version: 0.0.2
Summary: Is a package that simplifies accessing and managing Brazilian national holidays. It fetches holiday data directly from ANBIMA, allowing you to easily retrieve holiday dates, names, and weekdays, as well as check if a specific date is a holiday. The package offers a straightforward interface for querying and interacting with holiday information.
Author: Leonardo Alves Francisco
Author-email: leonardoalves294@gmail.com
License: MIT License
Keywords: holidays brazil national
